silverpeak_jira/__init__.py
silverpeak_jira/client.py
silverpeak_jira/config.py
silverpeak_jira/exceptions.py
silverpeak_jira/jirashell.py
silverpeak_jira/resilientsession.py
silverpeak_jira/resources.py
silverpeak_jira/utils/__init__.py
silverpeak_jira-2.0.0.1.dist-info/DESCRIPTION.rst
silverpeak_jira-2.0.0.1.dist-info/METADATA
silverpeak_jira-2.0.0.1.dist-info/RECORD
silverpeak_jira-2.0.0.1.dist-info/WHEEL
silverpeak_jira-2.0.0.1.dist-info/metadata.json
silverpeak_jira-2.0.0.1.dist-info/top_level.txt
