Metadata-Version: 2.0
Name: silverpeak-jira
Version: 2.0.0.1
Summary: Python library for interacting with JIRA via REST APIs.
Home-page: https://github.com/pycontribs/jira
Author: Ben Speakmon
Author-email: ben.speakmon@gmail.com
Maintainer: Tam Pham
Maintainer-email: tpham.corp@gmail.com
License: BSD
Project-URL: Bug Tracker, https://github.com/pycontribs/jira/issues
Project-URL: Source Code, https://github.com/pycontribs/jira.git
Project-URL: Documentation, https://jira.readthedocs.io/en/master/
Keywords: api,atlassian,jira,rest,web
Platform: UNKNOWN
Classifier: Development Status :: 5 - Production/Stable
Classifier: Environment :: Other Environment
Classifier: Intended Audience :: Developers
Classifier: Intended Audience :: Information Technology
Classifier: License :: OSI Approved :: BSD License
Classifier: Operating System :: OS Independent
Classifier: Programming Language :: Python
Classifier: Programming Language :: Python :: 2.7
Classifier: Programming Language :: Python :: 3
Classifier: Programming Language :: Python :: 3.4
Classifier: Programming Language :: Python :: 3.5
Classifier: Programming Language :: Python :: 3.6
Classifier: Programming Language :: Python :: 3.7
Classifier: Topic :: Software Development :: Libraries :: Python Modules
Classifier: Topic :: Internet :: WWW/HTTP
